Genetic_Programming.py
MAPSC45.py
MAPSDT.py
Training.py
data_load.py
functions.py
preProcessing.py
viztree.py
MAPSDT-3.0.5.dist-info/METADATA
MAPSDT-3.0.5.dist-info/WHEEL
MAPSDT-3.0.5.dist-info/top_level.txt
MAPSDT-3.0.5.dist-info/RECORD
