Metadata-Version: 2.1
Name: MAPSDT
Version: 3.0.5
Summary: MAPS Decision Tree
Home-page: https://github.com/Dongguk-MAPS/MAPSDT
Author: DGU MAPS LAB
Author-email: wjk1011@dgu.ac.kr
License: UNKNOWN
Keywords: MAPSDT
Platform: UNKNOWN
Classifier: Programming Language :: Python :: 3
Classifier: Programming Language :: Python :: 3.2
Classifier: Programming Language :: Python :: 3.3
Classifier: Programming Language :: Python :: 3.4
Classifier: Programming Language :: Python :: 3.5
Classifier: Programming Language :: Python :: 3.6
Classifier: Programming Language :: Python :: 3.7
Requires-Python: >=3
Requires-Dist: numpy
Requires-Dist: pandas
Requires-Dist: tqdm
Requires-Dist: graphviz
Requires-Dist: sympy
